LICENSE
MANIFEST.in
README.md
requirements.txt
setup.py
Schema/schema_authors.json
Schema/schema_concepts.json
Schema/schema_funders.json
Schema/schema_institutions.json
Schema/schema_publishers.json
Schema/schema_sources.json
Schema/schema_works.json
openalex_raw.egg-info/PKG-INFO
openalex_raw.egg-info/SOURCES.txt
openalex_raw.egg-info/dependency_links.txt
openalex_raw.egg-info/requires.txt
openalex_raw.egg-info/top_level.txt
openalexraw/__init__.py
openalexraw/archive.py
openalexraw/openalex.py