Metadata-Version: 2.1
Name: openalex-raw
Version: 0.3.2
Summary: Python library to access OpenAlex Snapshot files
Home-page: https://github.com/filipinascimento/openalex-raw
Author: Filipi N. Silva
Author-email: filipi@iu.edu
Classifier: Programming Language :: Python :: 3
Classifier: License :: OSI Approved :: MIT License
Classifier: Operating System :: OS Independent
Requires-Python: >=3.5
License-File: LICENSE
Requires-Dist: numpy
Requires-Dist: tqdm
Requires-Dist: ujson
Requires-Dist: dbgz
Requires-Dist: pandas
